gar/__init__.py
gar/gar.py
gar/py.typed
gar/trsgar.py
pygar_client-3.8.1.dist-info/METADATA
pygar_client-3.8.1.dist-info/WHEEL
pygar_client-3.8.1.dist-info/top_level.txt
pygar_client-3.8.1.dist-info/RECORD
