Metadata-Version: 2.1
Name: pygar-client
Version: 3.8.1
Summary: A Python client for the GAR protocol
Home-page: https://www.trinityriversystems.com/docs/gar_protocol/
Author: Jon Hill
